start_watching_case_list/__init__.py
start_watching_case_list/funcs/__init__.py
start_watching_case_list/funcs/auth.py
start_watching_case_list/funcs/query.py
start_watching_case_list/main.py
start_watching_case_list-0.1.8.dist-info/entry_points.txt
start_watching_case_list-0.1.8.dist-info/METADATA
start_watching_case_list-0.1.8.dist-info/WHEEL
start_watching_case_list-0.1.8.dist-info/RECORD
